[
{
  "model": "data_manager.theme",
  "pk": 1,
  "fields": {
    "display_name": "Map Layers",
    "name": "Property",
    "order": 0,
    "visible": true,
    "header_image": null,
    "header_attrib": null,
    "overview": "",
    "description": "",
    "thumbnail": null,
    "factsheet_thumb": null,
    "factsheet_link": null,
    "feature_image": null,
    "feature_excerpt": "",
    "feature_link": null,
    "site": [
      1
    ]
  }
},
{
  "model": "data_manager.layer",
  "pk": 1,
  "fields": {
    "name": "Tax Lots",
    "order": 0,
    "slug_name": "tax-lots",
    "layer_type": "XYZ",
    "url": "http://173.240.253.141/tiles/LOT_parcels/${z}/${x}/${y}.png",
    "shareable_url": true,
    "arcgis_layers": null,
    "disable_arcgis_attributes": false,
    "wms_slug": null,
    "wms_version": null,
    "is_sublayer": false,
    "search_query": false,
    "has_companion": false,
    "is_disabled": false,
    "disabled_message": null,
    "legend": null,
    "legend_title": null,
    "legend_subtitle": null,
    "utfurl": null,
    "description": "",
    "data_overview": "",
    "data_source": null,
    "data_notes": "",
    "bookmark": null,
    "kml": null,
    "data_download": null,
    "learn_more": null,
    "metadata": null,
    "source": null,
    "map_tiles": null,
    "thumbnail": null,
    "compress_display": false,
    "attribute_event": "click",
    "mouseover_field": null,
    "lookup_field": null,
    "is_annotated": false,
    "vector_outline_color": null,
    "vector_outline_opacity": null,
    "vector_color": null,
    "vector_fill": null,
    "vector_graphic": null,
    "point_radius": null,
    "opacity": 1.0,
    "site": [
      1
    ],
    "sublayers": [],
    "themes": [
      1
    ],
    "connect_companion_layers_to": [],
    "attribute_fields": [],
    "lookup_table": []
  }
},
{
  "model": "data_manager.layer",
  "pk": 3,
  "fields": {
    "name": "Slope",
    "order": 1,
    "slug_name": "slope",
    "layer_type": "XYZ",
    "url": "http://173.240.253.141/tiles/slope_Style/${z}/${x}/${y}.png",
    "shareable_url": true,
    "arcgis_layers": null,
    "disable_arcgis_attributes": false,
    "wms_slug": null,
    "wms_version": null,
    "is_sublayer": false,
    "search_query": false,
    "has_companion": false,
    "is_disabled": false,
    "disabled_message": null,
    "legend": "/static/landmapper/imgs/Slope_T.png",
    "legend_title": null,
    "legend_subtitle": null,
    "utfurl": null,
    "description": "",
    "data_overview": "",
    "data_source": null,
    "data_notes": "",
    "bookmark": null,
    "kml": null,
    "data_download": null,
    "learn_more": null,
    "metadata": null,
    "source": null,
    "map_tiles": null,
    "thumbnail": null,
    "compress_display": false,
    "attribute_event": "click",
    "mouseover_field": null,
    "lookup_field": null,
    "is_annotated": false,
    "vector_outline_color": null,
    "vector_outline_opacity": null,
    "vector_color": null,
    "vector_fill": null,
    "vector_graphic": null,
    "point_radius": null,
    "opacity": 0.5,
    "site": [
      1
    ],
    "sublayers": [],
    "themes": [
      1
    ],
    "connect_companion_layers_to": [],
    "attribute_fields": [],
    "lookup_table": []
  }
},
{
  "model": "data_manager.layer",
  "pk": 4,
  "fields": {
    "name": "Soils",
    "order": 3,
    "slug_name": "soils",
    "layer_type": "XYZ",
    "url": "http://173.240.253.141/tiles/soils/${z}/${x}/${y}.png",
    "shareable_url": true,
    "arcgis_layers": null,
    "disable_arcgis_attributes": false,
    "wms_slug": null,
    "wms_version": null,
    "is_sublayer": false,
    "search_query": false,
    "has_companion": false,
    "is_disabled": false,
    "disabled_message": null,
    "legend": "/static/landmapper/imgs/Soil_T.png",
    "legend_title": null,
    "legend_subtitle": null,
    "utfurl": null,
    "description": "",
    "data_overview": "",
    "data_source": null,
    "data_notes": "",
    "bookmark": null,
    "kml": null,
    "data_download": null,
    "learn_more": null,
    "metadata": null,
    "source": null,
    "map_tiles": null,
    "thumbnail": null,
    "compress_display": false,
    "attribute_event": "click",
    "mouseover_field": null,
    "lookup_field": null,
    "is_annotated": false,
    "vector_outline_color": null,
    "vector_outline_opacity": null,
    "vector_color": null,
    "vector_fill": null,
    "vector_graphic": null,
    "point_radius": null,
    "opacity": 0.7,
    "site": [
      1
    ],
    "sublayers": [],
    "themes": [
      1
    ],
    "connect_companion_layers_to": [],
    "attribute_fields": [],
    "lookup_table": []
  }
},
{
  "model": "data_manager.layer",
  "pk": 5,
  "fields": {
    "name": "Streams",
    "order": 5,
    "slug_name": "streams",
    "layer_type": "XYZ",
    "url": "http://173.240.253.141/tiles/streams/${z}/${x}/${y}.png",
    "shareable_url": true,
    "arcgis_layers": null,
    "disable_arcgis_attributes": false,
    "wms_slug": null,
    "wms_version": null,
    "is_sublayer": false,
    "search_query": false,
    "has_companion": false,
    "is_disabled": false,
    "disabled_message": null,
    "legend": "/static/landmapper/imgs/StreamsBoth_T.PNG",
    "legend_title": null,
    "legend_subtitle": null,
    "utfurl": null,
    "description": "",
    "data_overview": "",
    "data_source": null,
    "data_notes": "",
    "bookmark": null,
    "kml": null,
    "data_download": null,
    "learn_more": null,
    "metadata": null,
    "source": null,
    "map_tiles": null,
    "thumbnail": null,
    "compress_display": false,
    "attribute_event": "click",
    "mouseover_field": null,
    "lookup_field": null,
    "is_annotated": false,
    "vector_outline_color": null,
    "vector_outline_opacity": null,
    "vector_color": null,
    "vector_fill": null,
    "vector_graphic": null,
    "point_radius": null,
    "opacity": 1.0,
    "site": [
      1
    ],
    "sublayers": [],
    "themes": [
      1
    ],
    "connect_companion_layers_to": [],
    "attribute_fields": [],
    "lookup_table": []
  }
},
{
  "model": "data_manager.layer",
  "pk": 6,
  "fields": {
    "name": "County Boundaries",
    "order": 8,
    "slug_name": "county-boundaries",
    "layer_type": "ArcRest",
    "url": "http://navigator.state.or.us/ArcGIS/rest/services/Framework/Admin_Bounds_WM/MapServer/export",
    "shareable_url": true,
    "arcgis_layers": "6",
    "disable_arcgis_attributes": false,
    "wms_slug": null,
    "wms_version": null,
    "is_sublayer": false,
    "search_query": false,
    "has_companion": false,
    "is_disabled": false,
    "disabled_message": null,
    "legend": null,
    "legend_title": null,
    "legend_subtitle": null,
    "utfurl": null,
    "description": "Oregon county boundaries, maintained by DAS GEO.",
    "data_overview": "",
    "data_source": null,
    "data_notes": "",
    "bookmark": null,
    "kml": null,
    "data_download": "http://oe.oregonexplorer.info/ExternalContent/SpatialDataforDownload/orcnty2015.zip",
    "learn_more": null,
    "metadata": "http://spatialdata.oregonexplorer.info/geoportal/rest/document?id=%7B361C06FE-E9DE-4E24-A72E-280FB386A771%7D",
    "source": "http://spatialdata.oregonexplorer.info/geoportal/catalog/search/resource/details.page?uuid=%7B361C06FE-E9DE-4E24-A72E-280FB386A771%7D",
    "map_tiles": null,
    "thumbnail": null,
    "compress_display": false,
    "attribute_event": "click",
    "mouseover_field": null,
    "lookup_field": null,
    "is_annotated": false,
    "vector_outline_color": null,
    "vector_outline_opacity": null,
    "vector_color": null,
    "vector_fill": null,
    "vector_graphic": null,
    "point_radius": null,
    "opacity": 0.5,
    "site": [
      1
    ],
    "sublayers": [],
    "themes": [
      1
    ],
    "connect_companion_layers_to": [],
    "attribute_fields": [],
    "lookup_table": []
  }
},
{
  "model": "data_manager.layer",
  "pk": 7,
  "fields": {
    "name": "Soils [NW OR]",
    "order": 10,
    "slug_name": "soils-nw-or",
    "layer_type": "XYZ",
    "url": "http://173.240.253.141/tiles/NW_soil/${z}/${x}/${y}.png",
    "shareable_url": true,
    "arcgis_layers": null,
    "disable_arcgis_attributes": false,
    "wms_slug": null,
    "wms_version": null,
    "is_sublayer": false,
    "search_query": false,
    "has_companion": false,
    "is_disabled": false,
    "disabled_message": null,
    "legend": "/static/landmapper/imgs/Soil.PNG",
    "legend_title": null,
    "legend_subtitle": null,
    "utfurl": null,
    "description": "",
    "data_overview": "",
    "data_source": null,
    "data_notes": "",
    "bookmark": null,
    "kml": null,
    "data_download": null,
    "learn_more": null,
    "metadata": null,
    "source": null,
    "map_tiles": null,
    "thumbnail": null,
    "compress_display": false,
    "attribute_event": "click",
    "mouseover_field": null,
    "lookup_field": null,
    "is_annotated": false,
    "vector_outline_color": null,
    "vector_outline_opacity": null,
    "vector_color": null,
    "vector_fill": null,
    "vector_graphic": null,
    "point_radius": null,
    "opacity": 0.5,
    "site": [
      1
    ],
    "sublayers": [],
    "themes": [],
    "connect_companion_layers_to": [],
    "attribute_fields": [],
    "lookup_table": []
  }
},
{
  "model": "data_manager.layer",
  "pk": 8,
  "fields": {
    "name": "Soils [SW OR]",
    "order": 11,
    "slug_name": "soils-sw-or",
    "layer_type": "XYZ",
    "url": "http://173.240.253.141/tiles/SW_soil/${z}/${x}/${y}.png",
    "shareable_url": true,
    "arcgis_layers": null,
    "disable_arcgis_attributes": false,
    "wms_slug": null,
    "wms_version": null,
    "is_sublayer": false,
    "search_query": false,
    "has_companion": false,
    "is_disabled": false,
    "disabled_message": null,
    "legend": "/static/landmapper/imgs/Soil.PNG",
    "legend_title": null,
    "legend_subtitle": null,
    "utfurl": null,
    "description": "",
    "data_overview": "",
    "data_source": null,
    "data_notes": "",
    "bookmark": null,
    "kml": null,
    "data_download": null,
    "learn_more": null,
    "metadata": null,
    "source": null,
    "map_tiles": null,
    "thumbnail": null,
    "compress_display": false,
    "attribute_event": "click",
    "mouseover_field": null,
    "lookup_field": null,
    "is_annotated": false,
    "vector_outline_color": null,
    "vector_outline_opacity": null,
    "vector_color": null,
    "vector_fill": null,
    "vector_graphic": null,
    "point_radius": null,
    "opacity": 0.5,
    "site": [
      1
    ],
    "sublayers": [],
    "themes": [],
    "connect_companion_layers_to": [],
    "attribute_fields": [],
    "lookup_table": []
  }
},
{
  "model": "data_manager.layer",
  "pk": 9,
  "fields": {
    "name": "Soils [NE OR]",
    "order": 12,
    "slug_name": "soils-ne-or",
    "layer_type": "XYZ",
    "url": "http://173.240.253.141/tiles/NE_soil/${z}/${x}/${y}.png",
    "shareable_url": true,
    "arcgis_layers": null,
    "disable_arcgis_attributes": false,
    "wms_slug": null,
    "wms_version": null,
    "is_sublayer": false,
    "search_query": false,
    "has_companion": false,
    "is_disabled": false,
    "disabled_message": null,
    "legend": "/static/landmapper/imgs/Soil_T.PNG",
    "legend_title": null,
    "legend_subtitle": null,
    "utfurl": null,
    "description": "",
    "data_overview": "",
    "data_source": null,
    "data_notes": "",
    "bookmark": null,
    "kml": null,
    "data_download": null,
    "learn_more": null,
    "metadata": null,
    "source": null,
    "map_tiles": null,
    "thumbnail": null,
    "compress_display": false,
    "attribute_event": "click",
    "mouseover_field": null,
    "lookup_field": null,
    "is_annotated": false,
    "vector_outline_color": null,
    "vector_outline_opacity": null,
    "vector_color": null,
    "vector_fill": null,
    "vector_graphic": null,
    "point_radius": null,
    "opacity": 0.5,
    "site": [
      1
    ],
    "sublayers": [],
    "themes": [],
    "connect_companion_layers_to": [],
    "attribute_fields": [],
    "lookup_table": []
  }
},
{
  "model": "data_manager.layer",
  "pk": 10,
  "fields": {
    "name": "Soils [SE OR]",
    "order": 13,
    "slug_name": "soils-se-or",
    "layer_type": "XYZ",
    "url": "http://173.240.253.141/tiles/SE_soil/${z}/${x}/${y}.png",
    "shareable_url": true,
    "arcgis_layers": null,
    "disable_arcgis_attributes": false,
    "wms_slug": null,
    "wms_version": null,
    "is_sublayer": false,
    "search_query": false,
    "has_companion": false,
    "is_disabled": false,
    "disabled_message": null,
    "legend": "/static/landmapper/imgs/Soil_T.PNG",
    "legend_title": null,
    "legend_subtitle": null,
    "utfurl": null,
    "description": "",
    "data_overview": "",
    "data_source": null,
    "data_notes": "",
    "bookmark": null,
    "kml": null,
    "data_download": null,
    "learn_more": null,
    "metadata": null,
    "source": null,
    "map_tiles": null,
    "thumbnail": null,
    "compress_display": false,
    "attribute_event": "click",
    "mouseover_field": null,
    "lookup_field": null,
    "is_annotated": false,
    "vector_outline_color": null,
    "vector_outline_opacity": null,
    "vector_color": null,
    "vector_fill": null,
    "vector_graphic": null,
    "point_radius": null,
    "opacity": 0.5,
    "site": [
      1
    ],
    "sublayers": [],
    "themes": [],
    "connect_companion_layers_to": [],
    "attribute_fields": [],
    "lookup_table": []
  }
}
]
